goftests/__init__.py
goftests/test.py
goftests/utils.py
goftests-0.3.0.dist-info/LICENSE.txt
goftests-0.3.0.dist-info/METADATA
goftests-0.3.0.dist-info/WHEEL
goftests-0.3.0.dist-info/top_level.txt
goftests-0.3.0.dist-info/RECORD
