Metadata-Version: 2.1
Name: goftests
Version: 0.3.0
Summary: Goodness of fit tests for general datatypes
Home-page: https://github.com/posterior/goftests
Author: Fritz Obermeyer
Maintainer: Fritz Obermeyer
Maintainer-email: fritz.obermeyer@gmail.com
License: Revised BSD
Classifier: Development Status :: 4 - Beta
Classifier: License :: OSI Approved :: BSD License
Classifier: Operating System :: OS Independent
Classifier: Programming Language :: Python :: 3
License-File: LICENSE.txt
Requires-Dist: numpy
Requires-Dist: scipy
